ai_server/__init__.py
ai_server/py_client/__init__.py
ai_server/py_client/gaas/__init__.py
ai_server/py_client/gaas/database.py
ai_server/py_client/gaas/function.py
ai_server/py_client/gaas/model.py
ai_server/py_client/gaas/storage.py
ai_server/py_client/gaas/vector.py
ai_server/server_resources/__init__.py
ai_server/server_resources/server_client.py
ai_server/server_resources/server_proxy.py
ai_server/tests/__init__.py
ai_server/tests/all_tests.py
ai_server/tests/test_base_connection.py
ai_server/tests/test_database.py
ai_server/tests/test_langchain.py
ai_server/tests/test_model.py
ai_server/tests/test_openai_endpoints.py
ai_server/tests/test_run_pixel.py
ai_server/tests/test_storage.py
ai_server/tests/test_vector.py
ai_server/tests/variables.py
ai_server_sdk-0.0.27.dist-info/licenses/LICENSE
ai_server_sdk-0.0.27.dist-info/METADATA
ai_server_sdk-0.0.27.dist-info/WHEEL
ai_server_sdk-0.0.27.dist-info/top_level.txt
ai_server_sdk-0.0.27.dist-info/RECORD
