Metadata-Version: 2.4
Name: ai-server-sdk
Version: 0.0.27
Summary: Utility package to connect to AI Server instances.
Author: Thomas Trankle, Maher Khalil, Ryan Weiler
License-Expression: MIT
Project-URL: Homepage, https://github.com/SEMOSS/python-sdk
Project-URL: Repository, https://github.com/SEMOSS/python-sdk
Classifier: Typing :: Typed
Classifier: Intended Audience :: Developers
Classifier: Programming Language :: Python :: 3.10
Classifier: Programming Language :: Python :: 3.11
Classifier: Programming Language :: Python :: 3.12
Classifier: Programming Language :: Python :: 3.13
Classifier: Operating System :: OS Independent
Classifier: Operating System :: POSIX
Classifier: Operating System :: MacOS
Classifier: Operating System :: POSIX :: Linux
Classifier: Operating System :: Microsoft :: Windows
Requires-Python: >=3.10
License-File: LICENSE
Requires-Dist: requests
Requires-Dist: pandas
Requires-Dist: jsonpickle
Provides-Extra: full
Requires-Dist: langchain; extra == "full"
Requires-Dist: langchain-community; extra == "full"
Dynamic: license-file
